conTCP/__init__.py
conTCP/connect_TCP.py
TCPconnection-0.0.2.dist-info/METADATA
TCPconnection-0.0.2.dist-info/WHEEL
TCPconnection-0.0.2.dist-info/top_level.txt
TCPconnection-0.0.2.dist-info/RECORD
