Metadata-Version: 2.1
Name: TCPconnection
Version: 0.0.2
Summary: Simple TCP connection
Home-page: https://github.com/viniciusgcto/DIO/tree/main/Desafio_Pacotes_IMG_Python
Author: Vinicius Costa
Author-email: viniciusgcto@gmail.com
License: UNKNOWN
Platform: UNKNOWN
Requires-Python: >=3.8
